{
  "resourceType": "Patient",
  "id": "108636",
  "meta": {
    "versionId": "1",
    "lastUpdated": "2025-11-05T17:43:46.521+00:00",
    "source": "#jy8qVZnrjb8bxi0c"
  },
  "identifier": [
    {
      "system": "http://hospitalxyz.com/patients",
      "value": "arthas.menethil"
    }
  ],
  "name": [
    {
      "family": "Menethil",
      "given": ["Arthas"]
    }
  ],
  "telecom": [
    {
      "system": "phone",
      "value": "(212) 555-9876",
      "use": "mobile"
    },
    {
      "system": "email",
      "value": "arthas.new@hospitalxyz.com",
      "use": "home"
    }
  ],
  "gender": "male",
  "birthDate": "1985-06-14",
  "address": [
    {
      "use": "home",
      "type": "both",
      "line": ["77 Icecrown Boulevard"],
      "city": "Stormwind",
      "district": "Elwynn",
      "state": "NY",
      "postalCode": "10001",
      "country": "US",
      "period": {
        "start": "2025-11-05"
      }
    }
  ]
}
